<?xml version="1.0" encoding="utf-8"?>
<VärdepappersfondInnehav xmlns="http://schemas.fi.se/publika/vardepappersfonder/20200331">
  <Rapportinformation>
    <Kvartalsslut>2021-09-30</Kvartalsslut>
  </Rapportinformation>
  <Bolagsinformation>
    <Fondbolag_namn>Handelsbanken Fonder AB</Fondbolag_namn>
    <Fondbolag_institutnummer>58037</Fondbolag_institutnummer>
    <Fondbolag_LEI-kod>549300RJTULO02U5ZG71</Fondbolag_LEI-kod>
  </Bolagsinformation>
  <Fondinformation>
    <Fond_institutnummer>51199</Fond_institutnummer>
    <Fond_ISIN-kod>SE0000356099</Fond_ISIN-kod>
    <Fond_namn>Handelsbanken Japan Tema</Fond_namn>
    <Förvaltningsavgift>
      <MedAndelsklasser>
        <Förvaltningsavgift>
          <Andelsklass_namn>Handelsbanken Japan Tema A1 NOK</Andelsklass_namn>
          <Förvaltningsavgift_Typ>
            <Förvaltningsavgift_fast>1.60</Förvaltningsavgift_fast>
          </Förvaltningsavgift_Typ>
        </Förvaltningsavgift>
        <Förvaltningsavgift>
          <Andelsklass_namn>Handelsbanken Japan Tema A1 EUR</Andelsklass_namn>
          <Förvaltningsavgift_Typ>
            <Förvaltningsavgift_fast>1.60</Förvaltningsavgift_fast>
          </Förvaltningsavgift_Typ>
        </Förvaltningsavgift>
        <Förvaltningsavgift>
          <Andelsklass_namn>Handelsbanken Japan Tema A1 SEK</Andelsklass_namn>
          <Förvaltningsavgift_Typ>
            <Förvaltningsavgift_fast>1.60</Förvaltningsavgift_fast>
          </Förvaltningsavgift_Typ>
        </Förvaltningsavgift>
        <Förvaltningsavgift>
          <Andelsklass_namn>Handelsbanken Japan Tema A10 EUR</Andelsklass_namn>
          <Förvaltningsavgift_Typ>
            <Förvaltningsavgift_fast>0.60</Förvaltningsavgift_fast>
          </Förvaltningsavgift_Typ>
        </Förvaltningsavgift>
        <Förvaltningsavgift>
          <Andelsklass_namn>Handelsbanken Japan Tema A10 NOK</Andelsklass_namn>
          <Förvaltningsavgift_Typ>
            <Förvaltningsavgift_fast>0.60</Förvaltningsavgift_fast>
          </Förvaltningsavgift_Typ>
        </Förvaltningsavgift>
        <Förvaltningsavgift>
          <Andelsklass_namn>Handelsbanken Japan Tema A10 SEK</Andelsklass_namn>
          <Förvaltningsavgift_Typ>
            <Förvaltningsavgift_fast>0.60</Förvaltningsavgift_fast>
          </Förvaltningsavgift_Typ>
        </Förvaltningsavgift>
        <Förvaltningsavgift>
          <Andelsklass_namn>Handelsbanken Japan Tema A9 SEK</Andelsklass_namn>
          <Förvaltningsavgift_Typ>
            <Förvaltningsavgift_fast>0.80</Förvaltningsavgift_fast>
          </Förvaltningsavgift_Typ>
        </Förvaltningsavgift>
        <Förvaltningsavgift>
          <Andelsklass_namn>Handelsbanken Japan Tema A9 EUR</Andelsklass_namn>
          <Förvaltningsavgift_Typ>
            <Förvaltningsavgift_fast>0.80</Förvaltningsavgift_fast>
          </Förvaltningsavgift_Typ>
        </Förvaltningsavgift>
        <Förvaltningsavgift>
          <Andelsklass_namn>Handelsbanken Japan Tema B1 SEK</Andelsklass_namn>
          <Förvaltningsavgift_Typ>
            <Förvaltningsavgift_fast>1.60</Förvaltningsavgift_fast>
          </Förvaltningsavgift_Typ>
        </Förvaltningsavgift>
      </MedAndelsklasser>
    </Förvaltningsavgift>
    <Fondförmögenhet>6898089159</Fondförmögenhet>
    <Likvida_medel>201967671</Likvida_medel>
    <Övriga_tillgångar_och_skulder>55411562</Övriga_tillgångar_och_skulder>
    <Aktiv_risk>5.00</Aktiv_risk>
    <Standardavvikelse_24_månader>16.2900000000</Standardavvikelse_24_månader>
    <Jämförelseindex>
      <Jämförelseindex>Solactive ISS ESG Screened Japan Index NTR</Jämförelseindex>
    </Jämförelseindex>
    <FinansiellaInstrument>
      <FinansielltInstrument>
        <Tillgångsslag_enligt_LVF_5_kap>ÖverlåtbartVärdepapper</Tillgångsslag_enligt_LVF_5_kap>
        <Instrumentnamn>Amada</Instrumentnamn>
        <ISIN-kod_instrument>JP3122800000</ISIN-kod_instrument>
        <Landkod_Emittent>JP</Landkod_Emittent>
        <Valuta>JPY</Valuta>
        <Antal>1483944.0000000000</Antal>
        <Nominellt_belopp />
        <Kurs_som_använts_vid_värdering_av_instrumentet>1164.0000000000</Kurs_som_använts_vid_värdering_av_instrumentet>
        <Valutakurs_instrument>0.07840959000000000000</Valutakurs_instrument>
        <Marknadsvärde_instrument>135437732.89</Marknadsvärde_instrument>
        <Andel_av_fondförmögenhet_instrument>1.9600000000</Andel_av_fondförmögenhet_instrument>
        <Bransch>
          <Branschkod_instrument>20</Branschkod_instrument>
          <Bransch_namn_instrument>Industrials</Bransch_namn_instrument>
        </Bransch>
      </FinansielltInstrument>
      <FinansielltInstrument>
        <Tillgångsslag_enligt_LVF_5_kap>ÖverlåtbartVärdepapper</Tillgångsslag_enligt_LVF_5_kap>
        <Instrumentnamn>Ulvac Ord Shs</Instrumentnamn>
        <ISIN-kod_instrument>JP3126190002</ISIN-kod_instrument>
        <Landkod_Emittent>JP</Landkod_Emittent>
        <Valuta>JPY</Valuta>
        <Antal>249900.0000000000</Antal>
        <Nominellt_belopp />
        <Kurs_som_använts_vid_värdering_av_instrumentet>6410.0000000000</Kurs_som_använts_vid_värdering_av_instrumentet>
        <Valutakurs_instrument>0.07840959000000000000</Valutakurs_instrument>
        <Marknadsvärde_instrument>125601107.43</Marknadsvärde_instrument>
        <Andel_av_fondförmögenhet_instrument>1.8200000000</Andel_av_fondförmögenhet_instrument>
        <Bransch>
          <Branschkod_instrument>45</Branschkod_instrument>
          <Bransch_namn_instrument>Information Technology</Bransch_namn_instrument>
        </Bransch>
      </FinansielltInstrument>
      <FinansielltInstrument>
        <Tillgångsslag_enligt_LVF_5_kap>ÖverlåtbartVärdepapper</Tillgångsslag_enligt_LVF_5_kap>
        <Instrumentnamn>GMO Internet</Instrumentnamn>
        <ISIN-kod_instrument>JP3152750000</ISIN-kod_instrument>
        <Landkod_Emittent>JP</Landkod_Emittent>
        <Valuta>JPY</Valuta>
        <Antal>389032.0000000000</Antal>
        <Nominellt_belopp />
        <Kurs_som_använts_vid_värdering_av_instrumentet>2866.0000000000</Kurs_som_använts_vid_värdering_av_instrumentet>
        <Valutakurs_instrument>0.07840959000000000000</Valutakurs_instrument>
        <Marknadsvärde_instrument>87424004.34</Marknadsvärde_instrument>
        <Andel_av_fondförmögenhet_instrument>1.2700000000</Andel_av_fondförmögenhet_instrument>
        <Bransch>
          <Branschkod_instrument>45</Branschkod_instrument>
          <Bransch_namn_instrument>Information Technology</Bransch_namn_instrument>
        </Bransch>
      </FinansielltInstrument>
      <FinansielltInstrument>
        <Tillgångsslag_enligt_LVF_5_kap>ÖverlåtbartVärdepapper</Tillgångsslag_enligt_LVF_5_kap>
        <Instrumentnamn>Eisai</Instrumentnamn>
        <ISIN-kod_instrument>JP3160400002</ISIN-kod_instrument>
        <Landkod_Emittent>JP</Landkod_Emittent>
        <Valuta>JPY</Valuta>
        <Antal>75000.0000000000</Antal>
        <Nominellt_belopp />
        <Kurs_som_använts_vid_värdering_av_instrumentet>8396.0000000000</Kurs_som_använts_vid_värdering_av_instrumentet>
        <Valutakurs_instrument>0.07840959000000000000</Valutakurs_instrument>
        <Marknadsvärde_instrument>49374518.82</Marknadsvärde_instrument>
        <Andel_av_fondförmögenhet_instrument>0.7200000000</Andel_av_fondförmögenhet_instrument>
        <Bransch>
          <Branschkod_instrument>35</Branschkod_instrument>
          <Bransch_namn_instrument>Health Care</Bransch_namn_instrument>
        </Bransch>
      </FinansielltInstrument>
      <FinansielltInstrument>
        <Tillgångsslag_enligt_LVF_5_kap>ÖverlåtbartVärdepapper</Tillgångsslag_enligt_LVF_5_kap>
        <Instrumentnamn>Sre Holdings Ord Shs</Instrumentnamn>
        <ISIN-kod_instrument>JP3161320001</ISIN-kod_instrument>
        <Landkod_Emittent>JP</Landkod_Emittent>
        <Valuta>JPY</Valuta>
        <Antal>53000.0000000000</Antal>
        <Nominellt_belopp />
        <Kurs_som_använts_vid_värdering_av_instrumentet>7980.0000000000</Kurs_som_använts_vid_värdering_av_instrumentet>
        <Valutakurs_instrument>0.07840959000000000000</Valutakurs_instrument>
        <Marknadsvärde_instrument>33162551.99</Marknadsvärde_instrument>
        <Andel_av_fondförmögenhet_instrument>0.4800000000</Andel_av_fondförmögenhet_instrument>
        <Bransch>
          <Branschkod_instrument>60</Branschkod_instrument>
          <Bransch_namn_instrument>Real Estate</Bransch_namn_instrument>
        </Bransch>
      </FinansielltInstrument>
      <FinansielltInstrument>
        <Tillgångsslag_enligt_LVF_5_kap>ÖverlåtbartVärdepapper</Tillgångsslag_enligt_LVF_5_kap>
        <Instrumentnamn>SMS Ord Shs</Instrumentnamn>
        <ISIN-kod_instrument>JP3162350007</ISIN-kod_instrument>
        <Landkod_Emittent>JP</Landkod_Emittent>
        <Valuta>JPY</Valuta>
        <Antal>294000.0000000000</Antal>
        <Nominellt_belopp />
        <Kurs_som_använts_vid_värdering_av_instrumentet>4085.0000000000</Kurs_som_använts_vid_värdering_av_instrumentet>
        <Valutakurs_instrument>0.07840959000000000000</Valutakurs_instrument>
        <Marknadsvärde_instrument>94169133.49</Marknadsvärde_instrument>
        <Andel_av_fondförmögenhet_instrument>1.3700000000</Andel_av_fondförmögenhet_instrument>
        <Bransch>
          <Branschkod_instrument>20</Branschkod_instrument>
          <Bransch_namn_instrument>Industrials</Bransch_namn_instrument>
        </Bransch>
      </FinansielltInstrument>
      <FinansielltInstrument>
        <Tillgångsslag_enligt_LVF_5_kap>ÖverlåtbartVärdepapper</Tillgångsslag_enligt_LVF_5_kap>
        <Instrumentnamn>Open House</Instrumentnamn>
        <ISIN-kod_instrument>JP3173540000</ISIN-kod_instrument>
        <Landkod_Emittent>JP</Landkod_Emittent>
        <Valuta>JPY</Valuta>
        <Antal>280000.0000000000</Antal>
        <Nominellt_belopp />
        <Kurs_som_använts_vid_värdering_av_instrumentet>6620.0000000000</Kurs_som_använts_vid_värdering_av_instrumentet>
        <Valutakurs_instrument>0.07840959000000000000</Valutakurs_instrument>
        <Marknadsvärde_instrument>145340016.02</Marknadsvärde_instrument>
        <Andel_av_fondförmögenhet_instrument>2.1100000000</Andel_av_fondförmögenhet_instrument>
        <Bransch>
          <Branschkod_instrument>25</Branschkod_instrument>
          <Bransch_namn_instrument>Consumer Discretionary</Bransch_namn_instrument>
        </Bransch>
      </FinansielltInstrument>
      <FinansielltInstrument>
        <Tillgångsslag_enligt_LVF_5_kap>ÖverlåtbartVärdepapper</Tillgångsslag_enligt_LVF_5_kap>
        <Instrumentnamn>Obayashi</Instrumentnamn>
        <ISIN-kod_instrument>JP3190000004</ISIN-kod_instrument>
        <Landkod_Emittent>JP</Landkod_Emittent>
        <Valuta>JPY</Valuta>
        <Antal>1535000.0000000000</Antal>
        <Nominellt_belopp />
        <Kurs_som_använts_vid_värdering_av_instrumentet>929.0000000000</Kurs_som_använts_vid_värdering_av_instrumentet>
        <Valutakurs_instrument>0.07840959000000000000</Valutakurs_instrument>
        <Marknadsvärde_instrument>111813251.48</Marknadsvärde_instrument>
        <Andel_av_fondförmögenhet_instrument>1.6200000000</Andel_av_fondförmögenhet_instrument>
        <Bransch>
          <Branschkod_instrument>20</Branschkod_instrument>
          <Bransch_namn_instrument>Industrials</Bransch_namn_instrument>
        </Bransch>
      </FinansielltInstrument>
      <FinansielltInstrument>
        <Tillgångsslag_enligt_LVF_5_kap>ÖverlåtbartVärdepapper</Tillgångsslag_enligt_LVF_5_kap>
        <Instrumentnamn>Omron</Instrumentnamn>
        <ISIN-kod_instrument>JP3197800000</ISIN-kod_instrument>
        <Landkod_Emittent>JP</Landkod_Emittent>
        <Valuta>JPY</Valuta>
        <Antal>97000.0000000000</Antal>
        <Nominellt_belopp />
        <Kurs_som_använts_vid_värdering_av_instrumentet>11100.0000000000</Kurs_som_använts_vid_värdering_av_instrumentet>
        <Valutakurs_instrument>0.07840959000000000000</Valutakurs_instrument>
        <Marknadsvärde_instrument>84423605.55</Marknadsvärde_instrument>
        <Andel_av_fondförmögenhet_instrument>1.2200000000</Andel_av_fondförmögenhet_instrument>
        <Bransch>
          <Branschkod_instrument>45</Branschkod_instrument>
          <Bransch_namn_instrument>Information Technology</Bransch_namn_instrument>
        </Bransch>
      </FinansielltInstrument>
      <FinansielltInstrument>
        <Tillgångsslag_enligt_LVF_5_kap>ÖverlåtbartVärdepapper</Tillgångsslag_enligt_LVF_5_kap>
        <Instrumentnamn>Oriental Land</Instrumentnamn>
        <ISIN-kod_instrument>JP3198900007</ISIN-kod_instrument>
        <Landkod_Emittent>JP</Landkod_Emittent>
        <Valuta>JPY</Valuta>
        <Antal>125000.0000000000</Antal>
        <Nominellt_belopp />
        <Kurs_som_använts_vid_värdering_av_instrumentet>18130.0000000000</Kurs_som_använts_vid_värdering_av_instrumentet>
        <Valutakurs_instrument>0.07840959000000000000</Valutakurs_instrument>
        <Marknadsvärde_instrument>177695733.34</Marknadsvärde_instrument>
        <Andel_av_fondförmögenhet_instrument>2.5800000000</Andel_av_fondförmögenhet_instrument>
        <Bransch>
          <Branschkod_instrument>25</Branschkod_instrument>
          <Bransch_namn_instrument>Consumer Discretionary</Bransch_namn_instrument>
        </Bransch>
      </FinansielltInstrument>
      <FinansielltInstrument>
        <Tillgångsslag_enligt_LVF_5_kap>ÖverlåtbartVärdepapper</Tillgångsslag_enligt_LVF_5_kap>
        <Instrumentnamn>Orix</Instrumentnamn>
        <ISIN-kod_instrument>JP3200450009</ISIN-kod_instrument>
        <Landkod_Emittent>JP</Landkod_Emittent>
        <Valuta>JPY</Valuta>
        <Antal>690000.0000000000</Antal>
        <Nominellt_belopp />
        <Kurs_som_använts_vid_värdering_av_instrumentet>2110.0000000000</Kurs_som_använts_vid_värdering_av_instrumentet>
        <Valutakurs_instrument>0.07840959000000000000</Valutakurs_instrument>
        <Marknadsvärde_instrument>114156522.08</Marknadsvärde_instrument>
        <Andel_av_fondförmögenhet_instrument>1.6500000000</Andel_av_fondförmögenhet_instrument>
        <Bransch>
          <Branschkod_instrument>40</Branschkod_instrument>
          <Bransch_namn_instrument>Financials</Bransch_namn_instrument>
        </Bransch>
      </FinansielltInstrument>
      <FinansielltInstrument>
        <Tillgångsslag_enligt_LVF_5_kap>ÖverlåtbartVärdepapper</Tillgångsslag_enligt_LVF_5_kap>
        <Instrumentnamn>Kakaku.com Inc</Instrumentnamn>
        <ISIN-kod_instrument>JP3206000006</ISIN-kod_instrument>
        <Landkod_Emittent>JP</Landkod_Emittent>
        <Valuta>JPY</Valuta>
        <Antal>334000.0000000000</Antal>
        <Nominellt_belopp />
        <Kurs_som_använts_vid_värdering_av_instrumentet>3625.0000000000</Kurs_som_använts_vid_värdering_av_instrumentet>
        <Valutakurs_instrument>0.07840959000000000000</Valutakurs_instrument>
        <Marknadsvärde_instrument>94934411.09</Marknadsvärde_instrument>
        <Andel_av_fondförmögenhet_instrument>1.3800000000</Andel_av_fondförmögenhet_instrument>
        <Bransch>
          <Branschkod_instrument>50</Branschkod_instrument>
          <Bransch_namn_instrument>Telecommunication Services</Bransch_namn_instrument>
        </Bransch>
      </FinansielltInstrument>
      <FinansielltInstrument>
        <Tillgångsslag_enligt_LVF_5_kap>ÖverlåtbartVärdepapper</Tillgångsslag_enligt_LVF_5_kap>
        <Instrumentnamn>Keyence</Instrumentnamn>
        <ISIN-kod_instrument>JP3236200006</ISIN-kod_instrument>
        <Landkod_Emittent>JP</Landkod_Emittent>
        <Valuta>JPY</Valuta>
        <Antal>45000.0000000000</Antal>
        <Nominellt_belopp />
        <Kurs_som_använts_vid_värdering_av_instrumentet>67000.0000000000</Kurs_som_använts_vid_värdering_av_instrumentet>
        <Valutakurs_instrument>0.07840959000000000000</Valutakurs_instrument>
        <Marknadsvärde_instrument>236404913.85</Marknadsvärde_instrument>
        <Andel_av_fondförmögenhet_instrument>3.4300000000</Andel_av_fondförmögenhet_instrument>
        <Bransch>
          <Branschkod_instrument>45</Branschkod_instrument>
          <Bransch_namn_instrument>Information Technology</Bransch_namn_instrument>
        </Bransch>
      </FinansielltInstrument>
      <FinansielltInstrument>
        <Tillgångsslag_enligt_LVF_5_kap>ÖverlåtbartVärdepapper</Tillgångsslag_enligt_LVF_5_kap>
        <Instrumentnamn>Kubota</Instrumentnamn>
        <ISIN-kod_instrument>JP3266400005</ISIN-kod_instrument>
        <Landkod_Emittent>JP</Landkod_Emittent>
        <Valuta>JPY</Valuta>
        <Antal>810000.0000000000</Antal>
        <Nominellt_belopp />
        <Kurs_som_använts_vid_värdering_av_instrumentet>2389.0000000000</Kurs_som_använts_vid_värdering_av_instrumentet>
        <Valutakurs_instrument>0.07840959000000000000</Valutakurs_instrument>
        <Marknadsvärde_instrument>151729613.51</Marknadsvärde_instrument>
        <Andel_av_fondförmögenhet_instrument>2.2000000000</Andel_av_fondförmögenhet_instrument>
        <Bransch>
          <Branschkod_instrument>20</Branschkod_instrument>
          <Bransch_namn_instrument>Industrials</Bransch_namn_instrument>
        </Bransch>
      </FinansielltInstrument>
      <FinansielltInstrument>
        <Tillgångsslag_enligt_LVF_5_kap>ÖverlåtbartVärdepapper</Tillgångsslag_enligt_LVF_5_kap>
        <Instrumentnamn>Kurita Water Industry</Instrumentnamn>
        <ISIN-kod_instrument>JP3270000007</ISIN-kod_instrument>
        <Landkod_Emittent>JP</Landkod_Emittent>
        <Valuta>JPY</Valuta>
        <Antal>250000.0000000000</Antal>
        <Nominellt_belopp />
        <Kurs_som_använts_vid_värdering_av_instrumentet>5400.0000000000</Kurs_som_använts_vid_värdering_av_instrumentet>
        <Valutakurs_instrument>0.07840959000000000000</Valutakurs_instrument>
        <Marknadsvärde_instrument>105852946.50</Marknadsvärde_instrument>
        <Andel_av_fondförmögenhet_instrument>1.5300000000</Andel_av_fondförmögenhet_instrument>
        <Bransch>
          <Branschkod_instrument>20</Branschkod_instrument>
          <Bransch_namn_instrument>Industrials</Bransch_namn_instrument>
        </Bransch>
      </FinansielltInstrument>
      <FinansielltInstrument>
        <Tillgångsslag_enligt_LVF_5_kap>ÖverlåtbartVärdepapper</Tillgångsslag_enligt_LVF_5_kap>
        <Instrumentnamn>Shiseido</Instrumentnamn>
        <ISIN-kod_instrument>JP3351600006</ISIN-kod_instrument>
        <Landkod_Emittent>JP</Landkod_Emittent>
        <Valuta>JPY</Valuta>
        <Antal>177466.0000000000</Antal>
        <Nominellt_belopp />
        <Kurs_som_använts_vid_värdering_av_instrumentet>7537.0000000000</Kurs_som_använts_vid_värdering_av_instrumentet>
        <Valutakurs_instrument>0.07840959000000000000</Valutakurs_instrument>
        <Marknadsvärde_instrument>104877628.59</Marknadsvärde_instrument>
        <Andel_av_fondförmögenhet_instrument>1.5200000000</Andel_av_fondförmögenhet_instrument>
        <Bransch>
          <Branschkod_instrument>30</Branschkod_instrument>
          <Bransch_namn_instrument>Consumer Staples</Bransch_namn_instrument>
        </Bransch>
      </FinansielltInstrument>
      <FinansielltInstrument>
        <Tillgångsslag_enligt_LVF_5_kap>ÖverlåtbartVärdepapper</Tillgångsslag_enligt_LVF_5_kap>
        <Instrumentnamn>Shift Ord Shs</Instrumentnamn>
        <ISIN-kod_instrument>JP3355400007</ISIN-kod_instrument>
        <Landkod_Emittent>JP</Landkod_Emittent>
        <Valuta>JPY</Valuta>
        <Antal>35000.0000000000</Antal>
        <Nominellt_belopp />
        <Kurs_som_använts_vid_värdering_av_instrumentet>23790.0000000000</Kurs_som_använts_vid_värdering_av_instrumentet>
        <Valutakurs_instrument>0.07840959000000000000</Valutakurs_instrument>
        <Marknadsvärde_instrument>65287745.11</Marknadsvärde_instrument>
        <Andel_av_fondförmögenhet_instrument>0.9500000000</Andel_av_fondförmögenhet_instrument>
        <Bransch>
          <Branschkod_instrument>45</Branschkod_instrument>
          <Bransch_namn_instrument>Information Technology</Bransch_namn_instrument>
        </Bransch>
      </FinansielltInstrument>
      <FinansielltInstrument>
        <Tillgångsslag_enligt_LVF_5_kap>ÖverlåtbartVärdepapper</Tillgångsslag_enligt_LVF_5_kap>
        <Instrumentnamn>Shimadzu</Instrumentnamn>
        <ISIN-kod_instrument>JP3357200009</ISIN-kod_instrument>
        <Landkod_Emittent>JP</Landkod_Emittent>
        <Valuta>JPY</Valuta>
        <Antal>257000.0000000000</Antal>
        <Nominellt_belopp />
        <Kurs_som_använts_vid_värdering_av_instrumentet>4915.0000000000</Kurs_som_använts_vid_värdering_av_instrumentet>
        <Valutakurs_instrument>0.07840959000000000000</Valutakurs_instrument>
        <Marknadsvärde_instrument>99043465.66</Marknadsvärde_instrument>
        <Andel_av_fondförmögenhet_instrument>1.4400000000</Andel_av_fondförmögenhet_instrument>
        <Bransch>
          <Branschkod_instrument>45</Branschkod_instrument>
          <Bransch_namn_instrument>Information Technology</Bransch_namn_instrument>
        </Bransch>
      </FinansielltInstrument>
      <FinansielltInstrument>
        <Tillgångsslag_enligt_LVF_5_kap>ÖverlåtbartVärdepapper</Tillgångsslag_enligt_LVF_5_kap>
        <Instrumentnamn>Shimano</Instrumentnamn>
        <ISIN-kod_instrument>JP3358000002</ISIN-kod_instrument>
        <Landkod_Emittent>JP</Landkod_Emittent>
        <Valuta>JPY</Valuta>
        <Antal>46000.0000000000</Antal>
        <Nominellt_belopp />
        <Kurs_som_använts_vid_värdering_av_instrumentet>32900.0000000000</Kurs_som_använts_vid_värdering_av_instrumentet>
        <Valutakurs_instrument>0.07840959000000000000</Valutakurs_instrument>
        <Marknadsvärde_instrument>118665073.51</Marknadsvärde_instrument>
        <Andel_av_fondförmögenhet_instrument>1.7200000000</Andel_av_fondförmögenhet_instrument>
        <Bransch>
          <Branschkod_instrument>25</Branschkod_instrument>
          <Bransch_namn_instrument>Consumer Discretionary</Bransch_namn_instrument>
        </Bransch>
      </FinansielltInstrument>
      <FinansielltInstrument>
        <Tillgångsslag_enligt_LVF_5_kap>ÖverlåtbartVärdepapper</Tillgångsslag_enligt_LVF_5_kap>
        <Instrumentnamn>Sho-Bond Holdings Ord Shs</Instrumentnamn>
        <ISIN-kod_instrument>JP3360250009</ISIN-kod_instrument>
        <Landkod_Emittent>JP</Landkod_Emittent>
        <Valuta>JPY</Valuta>
        <Antal>143000.0000000000</Antal>
        <Nominellt_belopp />
        <Kurs_som_använts_vid_värdering_av_instrumentet>4960.0000000000</Kurs_som_använts_vid_värdering_av_instrumentet>
        <Valutakurs_instrument>0.07840959000000000000</Valutakurs_instrument>
        <Marknadsvärde_instrument>55614354.00</Marknadsvärde_instrument>
        <Andel_av_fondförmögenhet_instrument>0.8100000000</Andel_av_fondförmögenhet_instrument>
        <Bransch>
          <Branschkod_instrument>20</Branschkod_instrument>
          <Bransch_namn_instrument>Industrials</Bransch_namn_instrument>
        </Bransch>
      </FinansielltInstrument>
      <FinansielltInstrument>
        <Tillgångsslag_enligt_LVF_5_kap>ÖverlåtbartVärdepapper</Tillgångsslag_enligt_LVF_5_kap>
        <Instrumentnamn>Jmdc Ord Shs</Instrumentnamn>
        <ISIN-kod_instrument>JP3386690006</ISIN-kod_instrument>
        <Landkod_Emittent>JP</Landkod_Emittent>
        <Valuta>JPY</Valuta>
        <Antal>118000.0000000000</Antal>
        <Nominellt_belopp />
        <Kurs_som_använts_vid_värdering_av_instrumentet>7700.0000000000</Kurs_som_använts_vid_värdering_av_instrumentet>
        <Valutakurs_instrument>0.07840959000000000000</Valutakurs_instrument>
        <Marknadsvärde_instrument>71242953.47</Marknadsvärde_instrument>
        <Andel_av_fondförmögenhet_instrument>1.0300000000</Andel_av_fondförmögenhet_instrument>
        <Bransch>
          <Branschkod_instrument>35</Branschkod_instrument>
          <Bransch_namn_instrument>Health Care</Bransch_namn_instrument>
        </Bransch>
      </FinansielltInstrument>
      <FinansielltInstrument>
        <Tillgångsslag_enligt_LVF_5_kap>ÖverlåtbartVärdepapper</Tillgångsslag_enligt_LVF_5_kap>
        <Instrumentnamn>SCSK Ord Shs</Instrumentnamn>
        <ISIN-kod_instrument>JP3400400002</ISIN-kod_instrument>
        <Landkod_Emittent>JP</Landkod_Emittent>
        <Valuta>JPY</Valuta>
        <Antal>501900.0000000000</Antal>
        <Nominellt_belopp />
        <Kurs_som_använts_vid_värdering_av_instrumentet>2366.0000000000</Kurs_som_använts_vid_värdering_av_instrumentet>
        <Valutakurs_instrument>0.07840959000000000000</Valutakurs_instrument>
        <Marknadsvärde_instrument>93111027.44</Marknadsvärde_instrument>
        <Andel_av_fondförmögenhet_instrument>1.3500000000</Andel_av_fondförmögenhet_instrument>
        <Bransch>
          <Branschkod_instrument>45</Branschkod_instrument>
          <Bransch_namn_instrument>Information Technology</Bransch_namn_instrument>
        </Bransch>
      </FinansielltInstrument>
      <FinansielltInstrument>
        <Tillgångsslag_enligt_LVF_5_kap>ÖverlåtbartVärdepapper</Tillgångsslag_enligt_LVF_5_kap>
        <Instrumentnamn>Sosei Group Ord Shs</Instrumentnamn>
        <ISIN-kod_instrument>JP3431300007</ISIN-kod_instrument>
        <Landkod_Emittent>JP</Landkod_Emittent>
        <Valuta>JPY</Valuta>
        <Antal>280000.0000000000</Antal>
        <Nominellt_belopp />
        <Kurs_som_använts_vid_värdering_av_instrumentet>1905.0000000000</Kurs_som_använts_vid_värdering_av_instrumentet>
        <Valutakurs_instrument>0.07840959000000000000</Valutakurs_instrument>
        <Marknadsvärde_instrument>41823675.31</Marknadsvärde_instrument>
        <Andel_av_fondförmögenhet_instrument>0.6100000000</Andel_av_fondförmögenhet_instrument>
        <Bransch>
          <Branschkod_instrument>35</Branschkod_instrument>
          <Bransch_namn_instrument>Health Care</Bransch_namn_instrument>
        </Bransch>
      </FinansielltInstrument>
      <FinansielltInstrument>
        <Tillgångsslag_enligt_LVF_5_kap>ÖverlåtbartVärdepapper</Tillgångsslag_enligt_LVF_5_kap>
        <Instrumentnamn>Sony Group Corp Ord Shs</Instrumentnamn>
        <ISIN-kod_instrument>JP3435000009</ISIN-kod_instrument>
        <Landkod_Emittent>JP</Landkod_Emittent>
        <Valuta>JPY</Valuta>
        <Antal>335223.0000000000</Antal>
        <Nominellt_belopp />
        <Kurs_som_använts_vid_värdering_av_instrumentet>12455.0000000000</Kurs_som_använts_vid_värdering_av_instrumentet>
        <Valutakurs_instrument>0.07840959000000000000</Valutakurs_instrument>
        <Marknadsvärde_instrument>327375913.45</Marknadsvärde_instrument>
        <Andel_av_fondförmögenhet_instrument>4.7500000000</Andel_av_fondförmögenhet_instrument>
        <Bransch>
          <Branschkod_instrument>25</Branschkod_instrument>
          <Bransch_namn_instrument>Consumer Discretionary</Bransch_namn_instrument>
        </Bransch>
      </FinansielltInstrument>
      <FinansielltInstrument>
        <Tillgångsslag_enligt_LVF_5_kap>ÖverlåtbartVärdepapper</Tillgångsslag_enligt_LVF_5_kap>
        <Instrumentnamn>Takeda Pharmaceutical Co Ltd</Instrumentnamn>
        <ISIN-kod_instrument>JP3463000004</ISIN-kod_instrument>
        <Landkod_Emittent>JP</Landkod_Emittent>
        <Valuta>JPY</Valuta>
        <Antal>397300.0000000000</Antal>
        <Nominellt_belopp />
        <Kurs_som_använts_vid_värdering_av_instrumentet>3699.0000000000</Kurs_som_använts_vid_värdering_av_instrumentet>
        <Valutakurs_instrument>0.07840959000000000000</Valutakurs_instrument>
        <Marknadsvärde_instrument>115231729.27</Marknadsvärde_instrument>
        <Andel_av_fondförmögenhet_instrument>1.6700000000</Andel_av_fondförmögenhet_instrument>
        <Bransch>
          <Branschkod_instrument>35</Branschkod_instrument>
          <Bransch_namn_instrument>Health Care</Bransch_namn_instrument>
        </Bransch>
      </FinansielltInstrument>
      <FinansielltInstrument>
        <Tillgångsslag_enligt_LVF_5_kap>ÖverlåtbartVärdepapper</Tillgångsslag_enligt_LVF_5_kap>
        <Instrumentnamn>Daiichi Sankyo</Instrumentnamn>
        <ISIN-kod_instrument>JP3475350009</ISIN-kod_instrument>
        <Landkod_Emittent>JP</Landkod_Emittent>
        <Valuta>JPY</Valuta>
        <Antal>716000.0000000000</Antal>
        <Nominellt_belopp />
        <Kurs_som_använts_vid_värdering_av_instrumentet>2979.5000000000</Kurs_som_använts_vid_värdering_av_instrumentet>
        <Valutakurs_instrument>0.07840959000000000000</Valutakurs_instrument>
        <Marknadsvärde_instrument>167272903.36</Marknadsvärde_instrument>
        <Andel_av_fondförmögenhet_instrument>2.4200000000</Andel_av_fondförmögenhet_instrument>
        <Bransch>
          <Branschkod_instrument>35</Branschkod_instrument>
          <Bransch_namn_instrument>Health Care</Bransch_namn_instrument>
        </Bransch>
      </FinansielltInstrument>
      <FinansielltInstrument>
        <Tillgångsslag_enligt_LVF_5_kap>ÖverlåtbartVärdepapper</Tillgångsslag_enligt_LVF_5_kap>
        <Instrumentnamn>Daikin Industries</Instrumentnamn>
        <ISIN-kod_instrument>JP3481800005</ISIN-kod_instrument>
        <Landkod_Emittent>JP</Landkod_Emittent>
        <Valuta>JPY</Valuta>
        <Antal>83000.0000000000</Antal>
        <Nominellt_belopp />
        <Kurs_som_använts_vid_värdering_av_instrumentet>24460.0000000000</Kurs_som_använts_vid_värdering_av_instrumentet>
        <Valutakurs_instrument>0.07840959000000000000</Valutakurs_instrument>
        <Marknadsvärde_instrument>159185581.43</Marknadsvärde_instrument>
        <Andel_av_fondförmögenhet_instrument>2.3100000000</Andel_av_fondförmögenhet_instrument>
        <Bransch>
          <Branschkod_instrument>20</Branschkod_instrument>
          <Bransch_namn_instrument>Industrials</Bransch_namn_instrument>
        </Bransch>
      </FinansielltInstrument>
      <FinansielltInstrument>
        <Tillgångsslag_enligt_LVF_5_kap>ÖverlåtbartVärdepapper</Tillgångsslag_enligt_LVF_5_kap>
        <Instrumentnamn>Daifuku Ord Shs</Instrumentnamn>
        <ISIN-kod_instrument>JP3497400006</ISIN-kod_instrument>
        <Landkod_Emittent>JP</Landkod_Emittent>
        <Valuta>JPY</Valuta>
        <Antal>153000.0000000000</Antal>
        <Nominellt_belopp />
        <Kurs_som_använts_vid_värdering_av_instrumentet>10520.0000000000</Kurs_som_använts_vid_värdering_av_instrumentet>
        <Valutakurs_instrument>0.07840959000000000000</Valutakurs_instrument>
        <Marknadsvärde_instrument>126204939.68</Marknadsvärde_instrument>
        <Andel_av_fondförmögenhet_instrument>1.8300000000</Andel_av_fondförmögenhet_instrument>
        <Bransch>
          <Branschkod_instrument>20</Branschkod_instrument>
          <Bransch_namn_instrument>Industrials</Bransch_namn_instrument>
        </Bransch>
      </FinansielltInstrument>
      <FinansielltInstrument>
        <Tillgångsslag_enligt_LVF_5_kap>ÖverlåtbartVärdepapper</Tillgångsslag_enligt_LVF_5_kap>
        <Instrumentnamn>GLOBERIDE Ord Shs</Instrumentnamn>
        <ISIN-kod_instrument>JP3503800009</ISIN-kod_instrument>
        <Landkod_Emittent>JP</Landkod_Emittent>
        <Valuta>JPY</Valuta>
        <Antal>80000.0000000000</Antal>
        <Nominellt_belopp />
        <Kurs_som_använts_vid_värdering_av_instrumentet>3935.0000000000</Kurs_som_använts_vid_värdering_av_instrumentet>
        <Valutakurs_instrument>0.07840959000000000000</Valutakurs_instrument>
        <Marknadsvärde_instrument>24683338.93</Marknadsvärde_instrument>
        <Andel_av_fondförmögenhet_instrument>0.3600000000</Andel_av_fondförmögenhet_instrument>
        <Bransch>
          <Branschkod_instrument>25</Branschkod_instrument>
          <Bransch_namn_instrument>Consumer Discretionary</Bransch_namn_instrument>
        </Bransch>
      </FinansielltInstrument>
      <FinansielltInstrument>
        <Tillgångsslag_enligt_LVF_5_kap>ÖverlåtbartVärdepapper</Tillgångsslag_enligt_LVF_5_kap>
        <Instrumentnamn>TDK Ord Shs</Instrumentnamn>
        <ISIN-kod_instrument>JP3538800008</ISIN-kod_instrument>
        <Landkod_Emittent>JP</Landkod_Emittent>
        <Valuta>JPY</Valuta>
        <Antal>312000.0000000000</Antal>
        <Nominellt_belopp />
        <Kurs_som_använts_vid_värdering_av_instrumentet>4045.0000000000</Kurs_som_använts_vid_värdering_av_instrumentet>
        <Valutakurs_instrument>0.07840959000000000000</Valutakurs_instrument>
        <Marknadsvärde_instrument>98956038.96</Marknadsvärde_instrument>
        <Andel_av_fondförmögenhet_instrument>1.4300000000</Andel_av_fondförmögenhet_instrument>
        <Bransch>
          <Branschkod_instrument>45</Branschkod_instrument>
          <Bransch_namn_instrument>Information Technology</Bransch_namn_instrument>
        </Bransch>
      </FinansielltInstrument>
      <FinansielltInstrument>
        <Tillgångsslag_enligt_LVF_5_kap>ÖverlåtbartVärdepapper</Tillgångsslag_enligt_LVF_5_kap>
        <Instrumentnamn>TechnoPro Holdings Ord Shs</Instrumentnamn>
        <ISIN-kod_instrument>JP3545240008</ISIN-kod_instrument>
        <Landkod_Emittent>JP</Landkod_Emittent>
        <Valuta>JPY</Valuta>
        <Antal>381000.0000000000</Antal>
        <Nominellt_belopp />
        <Kurs_som_använts_vid_värdering_av_instrumentet>3385.0000000000</Kurs_som_använts_vid_värdering_av_instrumentet>
        <Valutakurs_instrument>0.07840959000000000000</Valutakurs_instrument>
        <Marknadsvärde_instrument>101123672.08</Marknadsvärde_instrument>
        <Andel_av_fondförmögenhet_instrument>1.4700000000</Andel_av_fondförmögenhet_instrument>
        <Bransch>
          <Branschkod_instrument>20</Branschkod_instrument>
          <Bransch_namn_instrument>Industrials</Bransch_namn_instrument>
        </Bransch>
      </FinansielltInstrument>
      <FinansielltInstrument>
        <Tillgångsslag_enligt_LVF_5_kap>ÖverlåtbartVärdepapper</Tillgångsslag_enligt_LVF_5_kap>
        <Instrumentnamn>Terumo</Instrumentnamn>
        <ISIN-kod_instrument>JP3546800008</ISIN-kod_instrument>
        <Landkod_Emittent>JP</Landkod_Emittent>
        <Valuta>JPY</Valuta>
        <Antal>327000.0000000000</Antal>
        <Nominellt_belopp />
        <Kurs_som_använts_vid_värdering_av_instrumentet>5285.0000000000</Kurs_som_använts_vid_värdering_av_instrumentet>
        <Valutakurs_instrument>0.07840959000000000000</Valutakurs_instrument>
        <Marknadsvärde_instrument>135507061.39</Marknadsvärde_instrument>
        <Andel_av_fondförmögenhet_instrument>1.9600000000</Andel_av_fondförmögenhet_instrument>
        <Bransch>
          <Branschkod_instrument>35</Branschkod_instrument>
          <Bransch_namn_instrument>Health Care</Bransch_namn_instrument>
        </Bransch>
      </FinansielltInstrument>
      <FinansielltInstrument>
        <Tillgångsslag_enligt_LVF_5_kap>ÖverlåtbartVärdepapper</Tillgångsslag_enligt_LVF_5_kap>
        <Instrumentnamn>Toyota Motor Ord Shs</Instrumentnamn>
        <ISIN-kod_instrument>JP3633400001</ISIN-kod_instrument>
        <Landkod_Emittent>JP</Landkod_Emittent>
        <Valuta>JPY</Valuta>
        <Antal>1225000.0000000000</Antal>
        <Nominellt_belopp />
        <Kurs_som_använts_vid_värdering_av_instrumentet>2000.0000000000</Kurs_som_använts_vid_värdering_av_instrumentet>
        <Valutakurs_instrument>0.07840959000000000000</Valutakurs_instrument>
        <Marknadsvärde_instrument>192103495.50</Marknadsvärde_instrument>
        <Andel_av_fondförmögenhet_instrument>2.7800000000</Andel_av_fondförmögenhet_instrument>
        <Bransch>
          <Branschkod_instrument>25</Branschkod_instrument>
          <Bransch_namn_instrument>Consumer Discretionary</Bransch_namn_instrument>
        </Bransch>
      </FinansielltInstrument>
      <FinansielltInstrument>
        <Tillgångsslag_enligt_LVF_5_kap>ÖverlåtbartVärdepapper</Tillgångsslag_enligt_LVF_5_kap>
        <Instrumentnamn>Toyota Industries</Instrumentnamn>
        <ISIN-kod_instrument>JP3634600005</ISIN-kod_instrument>
        <Landkod_Emittent>JP</Landkod_Emittent>
        <Valuta>JPY</Valuta>
        <Antal>173000.0000000000</Antal>
        <Nominellt_belopp />
        <Kurs_som_använts_vid_värdering_av_instrumentet>9200.0000000000</Kurs_som_använts_vid_värdering_av_instrumentet>
        <Valutakurs_instrument>0.07840959000000000000</Valutakurs_instrument>
        <Marknadsvärde_instrument>124796703.44</Marknadsvärde_instrument>
        <Andel_av_fondförmögenhet_instrument>1.8100000000</Andel_av_fondförmögenhet_instrument>
        <Bransch>
          <Branschkod_instrument>25</Branschkod_instrument>
          <Bransch_namn_instrument>Consumer Discretionary</Bransch_namn_instrument>
        </Bransch>
      </FinansielltInstrument>
      <FinansielltInstrument>
        <Tillgångsslag_enligt_LVF_5_kap>ÖverlåtbartVärdepapper</Tillgångsslag_enligt_LVF_5_kap>
        <Instrumentnamn>Pan Pacific International</Instrumentnamn>
        <ISIN-kod_instrument>JP3639650005</ISIN-kod_instrument>
        <Landkod_Emittent>JP</Landkod_Emittent>
        <Valuta>JPY</Valuta>
        <Antal>803000.0000000000</Antal>
        <Nominellt_belopp />
        <Kurs_som_använts_vid_värdering_av_instrumentet>2318.0000000000</Kurs_som_använts_vid_värdering_av_instrumentet>
        <Valutakurs_instrument>0.07840959000000000000</Valutakurs_instrument>
        <Marknadsvärde_instrument>145948003.98</Marknadsvärde_instrument>
        <Andel_av_fondförmögenhet_instrument>2.1200000000</Andel_av_fondförmögenhet_instrument>
        <Bransch>
          <Branschkod_instrument>25</Branschkod_instrument>
          <Bransch_namn_instrument>Consumer Discretionary</Bransch_namn_instrument>
        </Bransch>
      </FinansielltInstrument>
      <FinansielltInstrument>
        <Tillgångsslag_enligt_LVF_5_kap>ÖverlåtbartVärdepapper</Tillgångsslag_enligt_LVF_5_kap>
        <Instrumentnamn>Nihon M&amp;A Center Holdings Inc Ord Sh</Instrumentnamn>
        <ISIN-kod_instrument>JP3689050007</ISIN-kod_instrument>
        <Landkod_Emittent>JP</Landkod_Emittent>
        <Valuta>JPY</Valuta>
        <Antal>450000.0000000000</Antal>
        <Nominellt_belopp />
        <Kurs_som_använts_vid_värdering_av_instrumentet>3295.0000000000</Kurs_som_använts_vid_värdering_av_instrumentet>
        <Valutakurs_instrument>0.07840959000000000000</Valutakurs_instrument>
        <Marknadsvärde_instrument>116261819.57</Marknadsvärde_instrument>
        <Andel_av_fondförmögenhet_instrument>1.6900000000</Andel_av_fondförmögenhet_instrument>
        <Bransch>
          <Branschkod_instrument>20</Branschkod_instrument>
          <Bransch_namn_instrument>Industrials</Bransch_namn_instrument>
        </Bransch>
      </FinansielltInstrument>
      <FinansielltInstrument>
        <Tillgångsslag_enligt_LVF_5_kap>ÖverlåtbartVärdepapper</Tillgångsslag_enligt_LVF_5_kap>
        <Instrumentnamn>JCR Pharmaceuticals Ord Shs</Instrumentnamn>
        <ISIN-kod_instrument>JP3701000006</ISIN-kod_instrument>
        <Landkod_Emittent>JP</Landkod_Emittent>
        <Valuta>JPY</Valuta>
        <Antal>120000.0000000000</Antal>
        <Nominellt_belopp />
        <Kurs_som_använts_vid_värdering_av_instrumentet>2791.0000000000</Kurs_som_använts_vid_värdering_av_instrumentet>
        <Valutakurs_instrument>0.07840959000000000000</Valutakurs_instrument>
        <Marknadsvärde_instrument>26260939.88</Marknadsvärde_instrument>
        <Andel_av_fondförmögenhet_instrument>0.3800000000</Andel_av_fondförmögenhet_instrument>
        <Bransch>
          <Branschkod_instrument>35</Branschkod_instrument>
          <Bransch_namn_instrument>Health Care</Bransch_namn_instrument>
        </Bransch>
      </FinansielltInstrument>
      <FinansielltInstrument>
        <Tillgångsslag_enligt_LVF_5_kap>ÖverlåtbartVärdepapper</Tillgångsslag_enligt_LVF_5_kap>
        <Instrumentnamn>Nidec</Instrumentnamn>
        <ISIN-kod_instrument>JP3734800000</ISIN-kod_instrument>
        <Landkod_Emittent>JP</Landkod_Emittent>
        <Valuta>JPY</Valuta>
        <Antal>152037.0000000000</Antal>
        <Nominellt_belopp />
        <Kurs_som_använts_vid_värdering_av_instrumentet>12420.0000000000</Kurs_som_använts_vid_värdering_av_instrumentet>
        <Valutakurs_instrument>0.07840959000000000000</Valutakurs_instrument>
        <Marknadsvärde_instrument>148060792.73</Marknadsvärde_instrument>
        <Andel_av_fondförmögenhet_instrument>2.1500000000</Andel_av_fondförmögenhet_instrument>
        <Bransch>
          <Branschkod_instrument>20</Branschkod_instrument>
          <Bransch_namn_instrument>Industrials</Bransch_namn_instrument>
        </Bransch>
      </FinansielltInstrument>
      <FinansielltInstrument>
        <Tillgångsslag_enligt_LVF_5_kap>ÖverlåtbartVärdepapper</Tillgångsslag_enligt_LVF_5_kap>
        <Instrumentnamn>NTT</Instrumentnamn>
        <ISIN-kod_instrument>JP3735400008</ISIN-kod_instrument>
        <Landkod_Emittent>JP</Landkod_Emittent>
        <Valuta>JPY</Valuta>
        <Antal>460600.0000000000</Antal>
        <Nominellt_belopp />
        <Kurs_som_använts_vid_värdering_av_instrumentet>3085.0000000000</Kurs_som_använts_vid_värdering_av_instrumentet>
        <Valutakurs_instrument>0.07840959000000000000</Valutakurs_instrument>
        <Marknadsvärde_instrument>111416185.32</Marknadsvärde_instrument>
        <Andel_av_fondförmögenhet_instrument>1.6200000000</Andel_av_fondförmögenhet_instrument>
        <Bransch>
          <Branschkod_instrument>50</Branschkod_instrument>
          <Bransch_namn_instrument>Telecommunication Services</Bransch_namn_instrument>
        </Bransch>
      </FinansielltInstrument>
      <FinansielltInstrument>
        <Tillgångsslag_enligt_LVF_5_kap>ÖverlåtbartVärdepapper</Tillgångsslag_enligt_LVF_5_kap>
        <Instrumentnamn>Nintendo</Instrumentnamn>
        <ISIN-kod_instrument>JP3756600007</ISIN-kod_instrument>
        <Landkod_Emittent>JP</Landkod_Emittent>
        <Valuta>JPY</Valuta>
        <Antal>42000.0000000000</Antal>
        <Nominellt_belopp />
        <Kurs_som_använts_vid_värdering_av_instrumentet>54310.0000000000</Kurs_som_använts_vid_värdering_av_instrumentet>
        <Valutakurs_instrument>0.07840959000000000000</Valutakurs_instrument>
        <Marknadsvärde_instrument>178853842.98</Marknadsvärde_instrument>
        <Andel_av_fondförmögenhet_instrument>2.5900000000</Andel_av_fondförmögenhet_instrument>
        <Bransch>
          <Branschkod_instrument>50</Branschkod_instrument>
          <Bransch_namn_instrument>Telecommunication Services</Bransch_namn_instrument>
        </Bransch>
      </FinansielltInstrument>
      <FinansielltInstrument>
        <Tillgångsslag_enligt_LVF_5_kap>ÖverlåtbartVärdepapper</Tillgångsslag_enligt_LVF_5_kap>
        <Instrumentnamn>Nomura Research Institute</Instrumentnamn>
        <ISIN-kod_instrument>JP3762800005</ISIN-kod_instrument>
        <Landkod_Emittent>JP</Landkod_Emittent>
        <Valuta>JPY</Valuta>
        <Antal>388500.0000000000</Antal>
        <Nominellt_belopp />
        <Kurs_som_använts_vid_värdering_av_instrumentet>4140.0000000000</Kurs_som_använts_vid_värdering_av_instrumentet>
        <Valutakurs_instrument>0.07840959000000000000</Valutakurs_instrument>
        <Marknadsvärde_instrument>126113200.46</Marknadsvärde_instrument>
        <Andel_av_fondförmögenhet_instrument>1.8300000000</Andel_av_fondförmögenhet_instrument>
        <Bransch>
          <Branschkod_instrument>45</Branschkod_instrument>
          <Bransch_namn_instrument>Information Technology</Bransch_namn_instrument>
        </Bransch>
      </FinansielltInstrument>
      <FinansielltInstrument>
        <Tillgångsslag_enligt_LVF_5_kap>ÖverlåtbartVärdepapper</Tillgångsslag_enligt_LVF_5_kap>
        <Instrumentnamn>Bandai Namco Holdings Inc</Instrumentnamn>
        <ISIN-kod_instrument>JP3778630008</ISIN-kod_instrument>
        <Landkod_Emittent>JP</Landkod_Emittent>
        <Valuta>JPY</Valuta>
        <Antal>216616.0000000000</Antal>
        <Nominellt_belopp />
        <Kurs_som_använts_vid_värdering_av_instrumentet>8400.0000000000</Kurs_som_använts_vid_värdering_av_instrumentet>
        <Valutakurs_instrument>0.07840959000000000000</Valutakurs_instrument>
        <Marknadsvärde_instrument>142672082.68</Marknadsvärde_instrument>
        <Andel_av_fondförmögenhet_instrument>2.0700000000</Andel_av_fondförmögenhet_instrument>
        <Bransch>
          <Branschkod_instrument>25</Branschkod_instrument>
          <Bransch_namn_instrument>Consumer Discretionary</Bransch_namn_instrument>
        </Bransch>
      </FinansielltInstrument>
      <FinansielltInstrument>
        <Tillgångsslag_enligt_LVF_5_kap>ÖverlåtbartVärdepapper</Tillgångsslag_enligt_LVF_5_kap>
        <Instrumentnamn>Fanuc</Instrumentnamn>
        <ISIN-kod_instrument>JP3802400006</ISIN-kod_instrument>
        <Landkod_Emittent>JP</Landkod_Emittent>
        <Valuta>JPY</Valuta>
        <Antal>60000.0000000000</Antal>
        <Nominellt_belopp />
        <Kurs_som_använts_vid_värdering_av_instrumentet>24565.0000000000</Kurs_som_använts_vid_värdering_av_instrumentet>
        <Valutakurs_instrument>0.07840959000000000000</Valutakurs_instrument>
        <Marknadsvärde_instrument>115567894.70</Marknadsvärde_instrument>
        <Andel_av_fondförmögenhet_instrument>1.6800000000</Andel_av_fondförmögenhet_instrument>
        <Bransch>
          <Branschkod_instrument>20</Branschkod_instrument>
          <Bransch_namn_instrument>Industrials</Bransch_namn_instrument>
        </Bransch>
      </FinansielltInstrument>
      <FinansielltInstrument>
        <Tillgångsslag_enligt_LVF_5_kap>ÖverlåtbartVärdepapper</Tillgångsslag_enligt_LVF_5_kap>
        <Instrumentnamn>Fuji Corp</Instrumentnamn>
        <ISIN-kod_instrument>JP3809200003</ISIN-kod_instrument>
        <Landkod_Emittent>JP</Landkod_Emittent>
        <Valuta>JPY</Valuta>
        <Antal>230000.0000000000</Antal>
        <Nominellt_belopp />
        <Kurs_som_använts_vid_värdering_av_instrumentet>2867.0000000000</Kurs_som_använts_vid_värdering_av_instrumentet>
        <Valutakurs_instrument>0.07840959000000000000</Valutakurs_instrument>
        <Marknadsvärde_instrument>51704067.74</Marknadsvärde_instrument>
        <Andel_av_fondförmögenhet_instrument>0.7500000000</Andel_av_fondförmögenhet_instrument>
        <Bransch>
          <Branschkod_instrument>20</Branschkod_instrument>
          <Bransch_namn_instrument>Industrials</Bransch_namn_instrument>
        </Bransch>
      </FinansielltInstrument>
      <FinansielltInstrument>
        <Tillgångsslag_enligt_LVF_5_kap>ÖverlåtbartVärdepapper</Tillgångsslag_enligt_LVF_5_kap>
        <Instrumentnamn>Fujitsu</Instrumentnamn>
        <ISIN-kod_instrument>JP3818000006</ISIN-kod_instrument>
        <Landkod_Emittent>JP</Landkod_Emittent>
        <Valuta>JPY</Valuta>
        <Antal>108000.0000000000</Antal>
        <Nominellt_belopp />
        <Kurs_som_använts_vid_värdering_av_instrumentet>20310.0000000000</Kurs_som_använts_vid_värdering_av_instrumentet>
        <Valutakurs_instrument>0.07840959000000000000</Valutakurs_instrument>
        <Marknadsvärde_instrument>171989867.47</Marknadsvärde_instrument>
        <Andel_av_fondförmögenhet_instrument>2.4900000000</Andel_av_fondförmögenhet_instrument>
        <Bransch>
          <Branschkod_instrument>45</Branschkod_instrument>
          <Bransch_namn_instrument>Information Technology</Bransch_namn_instrument>
        </Bransch>
      </FinansielltInstrument>
      <FinansielltInstrument>
        <Tillgångsslag_enligt_LVF_5_kap>ÖverlåtbartVärdepapper</Tillgångsslag_enligt_LVF_5_kap>
        <Instrumentnamn>Hoya</Instrumentnamn>
        <ISIN-kod_instrument>JP3837800006</ISIN-kod_instrument>
        <Landkod_Emittent>JP</Landkod_Emittent>
        <Valuta>JPY</Valuta>
        <Antal>115000.0000000000</Antal>
        <Nominellt_belopp />
        <Kurs_som_använts_vid_värdering_av_instrumentet>17475.0000000000</Kurs_som_använts_vid_värdering_av_instrumentet>
        <Valutakurs_instrument>0.07840959000000000000</Valutakurs_instrument>
        <Marknadsvärde_instrument>157573872.30</Marknadsvärde_instrument>
        <Andel_av_fondförmögenhet_instrument>2.2800000000</Andel_av_fondförmögenhet_instrument>
        <Bransch>
          <Branschkod_instrument>35</Branschkod_instrument>
          <Bransch_namn_instrument>Health Care</Bransch_namn_instrument>
        </Bransch>
      </FinansielltInstrument>
      <FinansielltInstrument>
        <Tillgångsslag_enligt_LVF_5_kap>ÖverlåtbartVärdepapper</Tillgångsslag_enligt_LVF_5_kap>
        <Instrumentnamn>Mani Ord Shs</Instrumentnamn>
        <ISIN-kod_instrument>JP3869920003</ISIN-kod_instrument>
        <Landkod_Emittent>JP</Landkod_Emittent>
        <Valuta>JPY</Valuta>
        <Antal>150000.0000000000</Antal>
        <Nominellt_belopp />
        <Kurs_som_använts_vid_värdering_av_instrumentet>2134.0000000000</Kurs_som_använts_vid_värdering_av_instrumentet>
        <Valutakurs_instrument>0.07840959000000000000</Valutakurs_instrument>
        <Marknadsvärde_instrument>25098909.76</Marknadsvärde_instrument>
        <Andel_av_fondförmögenhet_instrument>0.3600000000</Andel_av_fondförmögenhet_instrument>
        <Bransch>
          <Branschkod_instrument>35</Branschkod_instrument>
          <Bransch_namn_instrument>Health Care</Bransch_namn_instrument>
        </Bransch>
      </FinansielltInstrument>
      <FinansielltInstrument>
        <Tillgångsslag_enligt_LVF_5_kap>ÖverlåtbartVärdepapper</Tillgångsslag_enligt_LVF_5_kap>
        <Instrumentnamn>MISUMI Group</Instrumentnamn>
        <ISIN-kod_instrument>JP3885400006</ISIN-kod_instrument>
        <Landkod_Emittent>JP</Landkod_Emittent>
        <Valuta>JPY</Valuta>
        <Antal>203000.0000000000</Antal>
        <Nominellt_belopp />
        <Kurs_som_använts_vid_värdering_av_instrumentet>4755.0000000000</Kurs_som_använts_vid_värdering_av_instrumentet>
        <Valutakurs_instrument>0.07840959000000000000</Valutakurs_instrument>
        <Marknadsvärde_instrument>75686032.89</Marknadsvärde_instrument>
        <Andel_av_fondförmögenhet_instrument>1.1000000000</Andel_av_fondförmögenhet_instrument>
        <Bransch>
          <Branschkod_instrument>20</Branschkod_instrument>
          <Bransch_namn_instrument>Industrials</Bransch_namn_instrument>
        </Bransch>
      </FinansielltInstrument>
      <FinansielltInstrument>
        <Tillgångsslag_enligt_LVF_5_kap>ÖverlåtbartVärdepapper</Tillgångsslag_enligt_LVF_5_kap>
        <Instrumentnamn>Sumitomo Mitsui Financial Group</Instrumentnamn>
        <ISIN-kod_instrument>JP3890350006</ISIN-kod_instrument>
        <Landkod_Emittent>JP</Landkod_Emittent>
        <Valuta>JPY</Valuta>
        <Antal>412800.0000000000</Antal>
        <Nominellt_belopp />
        <Kurs_som_använts_vid_värdering_av_instrumentet>3944.0000000000</Kurs_som_använts_vid_värdering_av_instrumentet>
        <Valutakurs_instrument>0.07840959000000000000</Valutakurs_instrument>
        <Marknadsvärde_instrument>127657336.20</Marknadsvärde_instrument>
        <Andel_av_fondförmögenhet_instrument>1.8500000000</Andel_av_fondförmögenhet_instrument>
        <Bransch>
          <Branschkod_instrument>40</Branschkod_instrument>
          <Bransch_namn_instrument>Financials</Bransch_namn_instrument>
        </Bransch>
      </FinansielltInstrument>
      <FinansielltInstrument>
        <Tillgångsslag_enligt_LVF_5_kap>ÖverlåtbartVärdepapper</Tillgångsslag_enligt_LVF_5_kap>
        <Instrumentnamn>Mitsubishi UFJ Financial Group</Instrumentnamn>
        <ISIN-kod_instrument>JP3902900004</ISIN-kod_instrument>
        <Landkod_Emittent>JP</Landkod_Emittent>
        <Valuta>JPY</Valuta>
        <Antal>3013332.0000000000</Antal>
        <Nominellt_belopp />
        <Kurs_som_använts_vid_värdering_av_instrumentet>657.9000000000</Kurs_som_använts_vid_värdering_av_instrumentet>
        <Valutakurs_instrument>0.07840959000000000000</Valutakurs_instrument>
        <Marknadsvärde_instrument>155444747.94</Marknadsvärde_instrument>
        <Andel_av_fondförmögenhet_instrument>2.2500000000</Andel_av_fondförmögenhet_instrument>
        <Bransch>
          <Branschkod_instrument>40</Branschkod_instrument>
          <Bransch_namn_instrument>Financials</Bransch_namn_instrument>
        </Bransch>
      </FinansielltInstrument>
      <FinansielltInstrument>
        <Tillgångsslag_enligt_LVF_5_kap>ÖverlåtbartVärdepapper</Tillgångsslag_enligt_LVF_5_kap>
        <Instrumentnamn>Minebea</Instrumentnamn>
        <ISIN-kod_instrument>JP3906000009</ISIN-kod_instrument>
        <Landkod_Emittent>JP</Landkod_Emittent>
        <Valuta>JPY</Valuta>
        <Antal>429000.0000000000</Antal>
        <Nominellt_belopp />
        <Kurs_som_använts_vid_värdering_av_instrumentet>2864.0000000000</Kurs_som_använts_vid_värdering_av_instrumentet>
        <Valutakurs_instrument>0.07840959000000000000</Valutakurs_instrument>
        <Marknadsvärde_instrument>96338413.21</Marknadsvärde_instrument>
        <Andel_av_fondförmögenhet_instrument>1.4000000000</Andel_av_fondförmögenhet_instrument>
        <Bransch>
          <Branschkod_instrument>20</Branschkod_instrument>
          <Bransch_namn_instrument>Industrials</Bransch_namn_instrument>
        </Bransch>
      </FinansielltInstrument>
      <FinansielltInstrument>
        <Tillgångsslag_enligt_LVF_5_kap>ÖverlåtbartVärdepapper</Tillgångsslag_enligt_LVF_5_kap>
        <Instrumentnamn>Mercari Rg</Instrumentnamn>
        <ISIN-kod_instrument>JP3921290007</ISIN-kod_instrument>
        <Landkod_Emittent>JP</Landkod_Emittent>
        <Valuta>JPY</Valuta>
        <Antal>183000.0000000000</Antal>
        <Nominellt_belopp />
        <Kurs_som_använts_vid_värdering_av_instrumentet>6160.0000000000</Kurs_som_använts_vid_värdering_av_instrumentet>
        <Valutakurs_instrument>0.07840959000000000000</Valutakurs_instrument>
        <Marknadsvärde_instrument>88389562.62</Marknadsvärde_instrument>
        <Andel_av_fondförmögenhet_instrument>1.2800000000</Andel_av_fondförmögenhet_instrument>
        <Bransch>
          <Branschkod_instrument>25</Branschkod_instrument>
          <Bransch_namn_instrument>Consumer Discretionary</Bransch_namn_instrument>
        </Bransch>
      </FinansielltInstrument>
      <FinansielltInstrument>
        <Tillgångsslag_enligt_LVF_5_kap>ÖverlåtbartVärdepapper</Tillgångsslag_enligt_LVF_5_kap>
        <Instrumentnamn>Yaskawa Electric Corp NPV</Instrumentnamn>
        <ISIN-kod_instrument>JP3932000007</ISIN-kod_instrument>
        <Landkod_Emittent>JP</Landkod_Emittent>
        <Valuta>JPY</Valuta>
        <Antal>124186.0000000000</Antal>
        <Nominellt_belopp />
        <Kurs_som_använts_vid_värdering_av_instrumentet>5400.0000000000</Kurs_som_använts_vid_värdering_av_instrumentet>
        <Valutakurs_instrument>0.07840959000000000000</Valutakurs_instrument>
        <Marknadsvärde_instrument>52581816.06</Marknadsvärde_instrument>
        <Andel_av_fondförmögenhet_instrument>0.7600000000</Andel_av_fondförmögenhet_instrument>
        <Bransch>
          <Branschkod_instrument>20</Branschkod_instrument>
          <Bransch_namn_instrument>Industrials</Bransch_namn_instrument>
        </Bransch>
      </FinansielltInstrument>
      <FinansielltInstrument>
        <Tillgångsslag_enligt_LVF_5_kap>ÖverlåtbartVärdepapper</Tillgångsslag_enligt_LVF_5_kap>
        <Instrumentnamn>KATITAS</Instrumentnamn>
        <ISIN-kod_instrument>JP3932950003</ISIN-kod_instrument>
        <Landkod_Emittent>JP</Landkod_Emittent>
        <Valuta>JPY</Valuta>
        <Antal>218000.0000000000</Antal>
        <Nominellt_belopp />
        <Kurs_som_använts_vid_värdering_av_instrumentet>3965.0000000000</Kurs_som_använts_vid_värdering_av_instrumentet>
        <Valutakurs_instrument>0.07840959000000000000</Valutakurs_instrument>
        <Marknadsvärde_instrument>67774897.31</Marknadsvärde_instrument>
        <Andel_av_fondförmögenhet_instrument>0.9800000000</Andel_av_fondförmögenhet_instrument>
        <Bransch>
          <Branschkod_instrument>60</Branschkod_instrument>
          <Bransch_namn_instrument>Real Estate</Bransch_namn_instrument>
        </Bransch>
      </FinansielltInstrument>
      <FinansielltInstrument>
        <Tillgångsslag_enligt_LVF_5_kap>ÖverlåtbartVärdepapper</Tillgångsslag_enligt_LVF_5_kap>
        <Instrumentnamn>Uni Charm</Instrumentnamn>
        <ISIN-kod_instrument>JP3951600000</ISIN-kod_instrument>
        <Landkod_Emittent>JP</Landkod_Emittent>
        <Valuta>JPY</Valuta>
        <Antal>340000.0000000000</Antal>
        <Nominellt_belopp />
        <Kurs_som_använts_vid_värdering_av_instrumentet>4949.0000000000</Kurs_som_använts_vid_värdering_av_instrumentet>
        <Valutakurs_instrument>0.07840959000000000000</Valutakurs_instrument>
        <Marknadsvärde_instrument>131936680.71</Marknadsvärde_instrument>
        <Andel_av_fondförmögenhet_instrument>1.9100000000</Andel_av_fondförmögenhet_instrument>
        <Bransch>
          <Branschkod_instrument>30</Branschkod_instrument>
          <Bransch_namn_instrument>Consumer Staples</Bransch_namn_instrument>
        </Bransch>
      </FinansielltInstrument>
      <FinansielltInstrument>
        <Tillgångsslag_enligt_LVF_5_kap>ÖverlåtbartVärdepapper</Tillgångsslag_enligt_LVF_5_kap>
        <Instrumentnamn>Recruit Holdings Ord Shs</Instrumentnamn>
        <ISIN-kod_instrument>JP3970300004</ISIN-kod_instrument>
        <Landkod_Emittent>JP</Landkod_Emittent>
        <Valuta>JPY</Valuta>
        <Antal>435000.0000000000</Antal>
        <Nominellt_belopp />
        <Kurs_som_använts_vid_värdering_av_instrumentet>6832.0000000000</Kurs_som_använts_vid_värdering_av_instrumentet>
        <Valutakurs_instrument>0.07840959000000000000</Valutakurs_instrument>
        <Marknadsvärde_instrument>233027028.71</Marknadsvärde_instrument>
        <Andel_av_fondförmögenhet_instrument>3.3800000000</Andel_av_fondförmögenhet_instrument>
        <Bransch>
          <Branschkod_instrument>20</Branschkod_instrument>
          <Bransch_namn_instrument>Industrials</Bransch_namn_instrument>
        </Bransch>
      </FinansielltInstrument>
      <FinansielltInstrument>
        <Tillgångsslag_enligt_LVF_5_kap>ÖverlåtbartVärdepapper</Tillgångsslag_enligt_LVF_5_kap>
        <Instrumentnamn>Rohm</Instrumentnamn>
        <ISIN-kod_instrument>JP3982800009</ISIN-kod_instrument>
        <Landkod_Emittent>JP</Landkod_Emittent>
        <Valuta>JPY</Valuta>
        <Antal>149500.0000000000</Antal>
        <Nominellt_belopp />
        <Kurs_som_använts_vid_värdering_av_instrumentet>10640.0000000000</Kurs_som_använts_vid_värdering_av_instrumentet>
        <Valutakurs_instrument>0.07840959000000000000</Valutakurs_instrument>
        <Marknadsvärde_instrument>124724566.62</Marknadsvärde_instrument>
        <Andel_av_fondförmögenhet_instrument>1.8100000000</Andel_av_fondförmögenhet_instrument>
        <Bransch>
          <Branschkod_instrument>45</Branschkod_instrument>
          <Bransch_namn_instrument>Information Technology</Bransch_namn_instrument>
        </Bransch>
      </FinansielltInstrument>
    </FinansiellaInstrument>
  </Fondinformation>
  <Fondinformation />
</VärdepappersfondInnehav>